all_parser/__init__.py
all_parser/all_parser_exceptions.py
all_parser/allparse.py
all_parser/allparse_utils.py
all_parser/cmd.py
all_parser/constants.py
all_parser/sub_parsers/__init__.py
all_parser/sub_parsers/csv_parser.py
all_parser/sub_parsers/docx_parser.py
all_parser/sub_parsers/json_parser.py
all_parser/sub_parsers/pdf_parser.py
all_parser/sub_parsers/xml_parser.py
all_parser/sub_parsers/yaml_parser.py
all_parser-0.1.1.dist-info/METADATA
all_parser-0.1.1.dist-info/WHEEL
all_parser-0.1.1.dist-info/entry_points.txt
all_parser-0.1.1.dist-info/top_level.txt
all_parser-0.1.1.dist-info/RECORD
