Metadata-Version: 2.1
Name: all-parser
Version: 0.1.1
Requires-Dist: click
Requires-Dist: python-docx
Requires-Dist: PyPDF2
Requires-Dist: PyYAML
